{
  "@context" : "http://iiif.io/api/presentation/2/context.json",
  "@id" : "https://JennyNW.github.io/Peacock/manifests/Peacockmanifest4.json",
  "@type" : "sc:Manifest",
  "viewingHint" : "individuals",
  "label" : "Jenny's peacocks",
  "metadata" : [ ],
  "description" : [ {
    "@value" : "[Three pictures of peacocks]",
    "@language" : "en"
  } ],
  "license" : "https://creativecommons.org/licenses/by/3.0/",
  "attribution" : "[QDL images]",
  "sequences" : [ {
    "@id" : "http://102619ad-c6da-4a2d-ac11-3378ab9bf72f",
    "@type" : "sc:Sequence",
    "label" : [ {
      "@value" : "Normal Sequence",
      "@language" : "en"
    } ],
    "canvases" : [ {
      "@id" : "http://f4ab262c-23cd-46b0-8b10-fe2e69efdcd8",
      "@type" : "sc:Canvas",
      "label" : "The Peacock from Or 2784",
      "height" : 1200,
      "width" : 818,
      "images" : [ {
        "@context" : "http://iiif.io/api/presentation/2/context.json",
        "@id" : "http://227be1fc-2c1c-4646-8a85-434f5c1d2e4b",
        "@type" : "oa:Annotation",
        "motivation" : "sc:painting",
        "resource" : {
          "@id" : "https://jennynw.github.io/Peacock/images/Or2784_0472Peacock/full/full/0/default.jpg",
          "@type" : "dctypes:Image",
          "format" : "image/jpeg",
          "service" : {
            "@context" : "http://iiif.io/api/image/2/context.json",
            "@id" : "https://jennynw.github.io/Peacock/images/Or2784_0472Peacock",
            "profile" : "http://iiif.io/api/image/2/level0.json"
          },
          "height" : 1200,
          "width" : 818
        },
        "on" : "http://f4ab262c-23cd-46b0-8b10-fe2e69efdcd8"
      } ],
      "related" : ""
    }, {
      "@id" : "http://bb3531ab-bec0-41e8-92ed-2a4d46915e0b",
      "@type" : "sc:Canvas",
      "label" : "The Peacock from Or 1621",
      "height" : 1200,
      "width" : 846,
      "images" : [ {
        "@context" : "http://iiif.io/api/presentation/2/context.json",
        "@id" : "http://3b1bc5df-9b99-46cf-95ed-26e3534b27e5",
        "@type" : "oa:Annotation",
        "motivation" : "sc:painting",
        "resource" : {
          "@id" : "https://jennynw.github.io/Peacock/images/Or1621_0796Peacock/full/full/0/default.jpg",
          "@type" : "dctypes:Image",
          "format" : "image/jpeg",
          "service" : {
            "@context" : "http://iiif.io/api/image/2/context.json",
            "@id" : "https://jennynw.github.io/Peacock/images/Or1621_0796Peacock",
            "profile" : "http://iiif.io/api/image/2/level0.json"
          },
          "height" : 1200,
          "width" : 846
        },
        "on" : "http://bb3531ab-bec0-41e8-92ed-2a4d46915e0b"
      } ],
      "related" : ""
    }, {
      "@id" : "http://06efe9f0-0851-4eac-ad25-a4cc8cf8d386",
      "@type" : "sc:Canvas",
      "label" : " The Peacock from Or 14140",
      "height" : 1200,
      "width" : 809,
      "images" : [ {
        "@context" : "http://iiif.io/api/presentation/2/context.json",
        "@id" : "http://57a818c6-a0e1-4868-b36b-f35d4936bbf6",
        "@type" : "oa:Annotation",
        "motivation" : "sc:painting",
        "resource" : {
          "@id" : "https://jennynw.github.io/Peacock/images/Or14140_0241Peacock/full/full/0/default.jpg",
          "@type" : "dctypes:Image",
          "format" : "image/jpeg",
          "service" : {
            "@context" : "http://iiif.io/api/image/2/context.json",
            "@id" : "https://jennynw.github.io/Peacock/images/Or14140_0241Peacock",
            "profile" : "http://iiif.io/api/image/2/level0.json"
          },
          "height" : 1200,
          "width" : 809
        },
        "on" : "http://06efe9f0-0851-4eac-ad25-a4cc8cf8d386"
      } ],
      "related" : ""
    } ]
  } ],
  "structures" : [ {
    "@id" : "http://example.org/iiif/book1/range/top",
    "@type" : "sc:Range",
    "label" : "Table of Content",
    "viewingHint" : "top",
    "ranges" : [ "http://example.org/iiif/book1/range/intro", "http://example.org/iiif/book1/range/chapter2" ]
  }, {
    "@id" : "http://example.org/iiif/book1/range/intro",
    "@type" : "sc:Range",
    "label" : "Introduction",
    "canvases" : [ "http://f4ab262c-23cd-46b0-8b10-fe2e69efdcd8" ]
  }, {
    "@id" : "http://example.org/iiif/book1/range/chapter2",
    "@type" : "sc:Range",
    "label" : "Chapter 2",
    "canvases" : [ "http://06efe9f0-0851-4eac-ad25-a4cc8cf8d386" ]
  } ]
}